abstract_images/__init__.py
abstract_images/image_utils.py
abstract_images/pdf_module.py
abstract_images/pdf_utils.py
abstract_images/consoles/__init__.py
abstract_images/consoles/imageViewerTab/__init__.py
abstract_images/consoles/imageViewerTab/functions.py
abstract_images/consoles/imageViewerTab/imports.py
abstract_images/consoles/imageViewerTab/initFuncs.py
abstract_images/consoles/imageViewerTab/main.py
abstract_images/green_screen_delimiter/__init__.py
abstract_images/green_screen_delimiter/compare_screens.py
abstract_images/green_screen_delimiter/detect_allgreen.py
abstract_images/green_screen_delimiter/detect_green_screen_blur.py
abstract_images/green_screen_delimiter/get_new_imagepath.py
abstract_images-0.0.8.dist-info/METADATA
abstract_images-0.0.8.dist-info/WHEEL
abstract_images-0.0.8.dist-info/top_level.txt
abstract_images-0.0.8.dist-info/RECORD
