Metadata-Version: 2.4
Name: abstract_images
Version: 0.0.8
Summary: This module, part of the `abstract_essentials` package,
Home-page: https://github.com/AbstractEndeavors/abstract_images
Author: putkoff
Author-email: partners@abstractendeavors.com
Classifier: Development Status :: 3 - Alpha
Classifier: Intended Audience :: Developers
Classifier: License :: OSI Approved :: MIT License
Classifier: Programming Language :: Python :: 3
Classifier: Programming Language :: Python :: 3.11
Requires-Python: >=3.6
Dynamic: author
Dynamic: author-email
Dynamic: classifier
Dynamic: description-content-type
Dynamic: home-page
Dynamic: requires-python
Dynamic: summary
